pyeasyrpc/__init__.py
pyeasyrpc/redis_connection.py
pyeasyrpc/rpc.py
pyeasyrpc/rpc_data.py
pyeasyrpc/rpc_manager.py
pyeasyrpc/singleton.py
pyeasyrpc/redis_collections/__init__.py
pyeasyrpc/redis_collections/dict.py
pyeasyrpc/redis_collections/list.py
pyeasyrpc/redis_collections/mailbox.py
pyeasyrpc/redis_collections/queue.py
pyeasyrpc/redis_collections/redis_object.py
pyeasyrpc/redis_collections/set.py
tests/__init__.py
tests/test_redis_manager.py
tests/test_rpc.py
tests/test_redis_collections/__init__.py
tests/test_redis_collections/test_dict.py
tests/test_redis_collections/test_list.py
tests/test_redis_collections/test_mailbox.py
tests/test_redis_collections/test_queue.py
tests/test_redis_collections/test_redis_object.py
tests/test_redis_collections/test_set.py
pyeasyrpc-0.0.1.dist-info/LICENSE
pyeasyrpc-0.0.1.dist-info/METADATA
pyeasyrpc-0.0.1.dist-info/WHEEL
pyeasyrpc-0.0.1.dist-info/top_level.txt
pyeasyrpc-0.0.1.dist-info/RECORD
