Metadata-Version: 2.1
Name: pyeasyrpc
Version: 0.0.1
Summary: a Python RPC framework using redis
Home-page: https://github.com/wo1fsea/PyEasyRPC
Author: Quanyong Huang
Author-email: quanyongh@foxmail.com
License: MIT
Download-URL: https://github.com/wo1fsea/PyEasyRPC/releases/tag/v0.0.1
Keywords: rpc-framework,redis
Platform: UNKNOWN
Classifier: Programming Language :: Python :: 3.5
Classifier: Programming Language :: Python :: 3.6
Classifier: Programming Language :: Python :: 3.7
Classifier: License :: OSI Approved :: MIT License
Classifier: Operating System :: OS Independent
Requires-Dist: msgpack-python
Requires-Dist: shortuuid
Requires-Dist: redis
